deberta_emotion_predictor/__init__.py
deberta_emotion_predictor/deberta_emotion_predictor.py
deberta_emotion_predictor-1.2.0.dist-info/LICENSE
deberta_emotion_predictor-1.2.0.dist-info/METADATA
deberta_emotion_predictor-1.2.0.dist-info/WHEEL
deberta_emotion_predictor-1.2.0.dist-info/top_level.txt
deberta_emotion_predictor-1.2.0.dist-info/RECORD
