Metadata-Version: 2.2
Name: deberta_emotion_predictor
Version: 1.2.0
Summary: A DeBERTa-based emotion predictor for Japanese text.
Home-page: https://huggingface.co/YoichiTakenaka/deverta-v3-japanese-large-Joy
Author: takenaka Yoichi
Author-email: takenaka@kansai-u.ac.jp
Classifier: Programming Language :: Python :: 3
Classifier: License :: OSI Approved :: MIT License
Classifier: Operating System :: OS Independent
Requires-Python: >=3.6
License-File: LICENSE
Requires-Dist: torch
Requires-Dist: transformers
Requires-Dist: pandas
Dynamic: author
Dynamic: author-email
Dynamic: classifier
Dynamic: description
Dynamic: description-content-type
Dynamic: home-page
Dynamic: requires-dist
Dynamic: requires-python
Dynamic: summary
